_examples/__init__.py
examples/__init__.py
plufthesis/__init__.py
plufthesis/config.py
plufthesis/doc_class_type.py
plufthesis/info_models.py
plufthesis/thesis.py
plufthesis/transformers.py
plufthesis/assets/ufdissertation.cls
tests/__init__.py
tests/config.py
tests/test_thesis.py
tests/test_transformers.py
tests/fixtures/__init__.py
tests/fixtures/thesis.py
tests/utils/__init__.py
tests/utils/doc.py
tests/utils/pdf.py
pl_uf_thesis-0.2.0.dist-info/LICENSE.md
pl_uf_thesis-0.2.0.dist-info/METADATA
pl_uf_thesis-0.2.0.dist-info/WHEEL
pl_uf_thesis-0.2.0.dist-info/entry_points.txt
pl_uf_thesis-0.2.0.dist-info/top_level.txt
pl_uf_thesis-0.2.0.dist-info/RECORD
