Metadata-Version: 2.1
Name: pl-uf-thesis
Version: 0.2.0
Summary: University of Florida Thesis/Dissertation Template for Pyexlatex
Home-page: https://github.com/nickderobertis/pl-uf-thesis
Author: Nick DeRobertis
Author-email: whoopnip@gmail.com
License: MIT
Project-URL: Code, https://github.com/nickderobertis/pl-uf-thesis
Project-URL: Documentation, https://nickderobertis.github.io/pl-uf-thesis
Platform: UNKNOWN
Classifier: Development Status :: 3 - Alpha
Classifier: Intended Audience :: Developers
Classifier: Programming Language :: Python :: 3.6
Classifier: Programming Language :: Python :: 3.7
Requires-Dist: pyexlatex
